{
  "lexicon": 1,
  "id": "app.rocksky.library.getAlbumInfo",
  "defs": {
    "main": {
      "type": "query",
      "description": "Get album notes, images and similar info.",
      "parameters": {
        "type": "params",
        "required": [
          "id"
        ],
        "properties": {
          "id": {
            "type": "string",
            "description": "The album id"
          }
        }
      },
      "output": {
        "encoding": "application/json",
        "schema": {
          "type": "object",
          "properties": {}
        }
      }
    }
  }
}
